<?xml version="1.0" encoding="UTF-8"?>
<AWIZO>
    <DOCUMENT>
	<TITLE>Awizo</TITLE>
	<RECIPIENT_EMAIL>pawel.maciejewski@spmtdbd03</RECIPIENT_EMAIL>
<!--	<RECIPIENT_SMS>694596782</RECIPIENT_SMS>-->
	<SENDER>SYSTEM</SENDER>
        <TEMPLATENAME>Elektroniczne awizo zbiorcze</TEMPLATENAME>
        <TEMPLATEVERSION>1.0</TEMPLATEVERSION>
        <LANGUAGE>PL</LANGUAGE>    
	<METADATA source_type="inline">
	    <NUMER_FAKTURY>F/1123123/02/10</NUMER_FAKTURY>
	    <DATA_WYSTAWIENIA>2010-02-03</DATA_WYSTAWIENIA>
	    <DATA_PLATNOSCI>2010-02-17</DATA_PLATNOSCI>
	    <KWOTA_PLATNOSCI>78,00</KWOTA_PLATNOSCI>
	    <FORMA_PLATNOSCI>przelew</FORMA_PLATNOSCI>
	</METADATA>
    </DOCUMENT>
</AWIZO>
